gym_drake_lca/__init__.py
gym_drake_lca/assets/blue_cube.sdf
gym_drake_lca/assets/collision_ground_plane.sdf
gym_drake_lca/assets/env_256_brick_room.jpg
gym_drake_lca/assets/follower_arm.sdf
gym_drake_lca/assets/follower_meshes/base_link.STL
gym_drake_lca/assets/follower_meshes/base_link_collision.mtl
gym_drake_lca/assets/follower_meshes/base_link_collision.obj
gym_drake_lca/assets/follower_meshes/base_link_collision.stl
gym_drake_lca/assets/follower_meshes/base_link_motor.STL
gym_drake_lca/assets/follower_meshes/link_1.STL
gym_drake_lca/assets/follower_meshes/link_1_collision.mtl
gym_drake_lca/assets/follower_meshes/link_1_collision.obj
gym_drake_lca/assets/follower_meshes/link_1_collision.stl
gym_drake_lca/assets/follower_meshes/link_1_motor.STL
gym_drake_lca/assets/follower_meshes/link_2.STL
gym_drake_lca/assets/follower_meshes/link_2_collision.mtl
gym_drake_lca/assets/follower_meshes/link_2_collision.obj
gym_drake_lca/assets/follower_meshes/link_2_collision.stl
gym_drake_lca/assets/follower_meshes/link_2_motor.STL
gym_drake_lca/assets/follower_meshes/link_3.STL
gym_drake_lca/assets/follower_meshes/link_3_collision.mtl
gym_drake_lca/assets/follower_meshes/link_3_collision.obj
gym_drake_lca/assets/follower_meshes/link_3_collision.stl
gym_drake_lca/assets/follower_meshes/link_3_motor.STL
gym_drake_lca/assets/follower_meshes/link_4.STL
gym_drake_lca/assets/follower_meshes/link_4_collision.mtl
gym_drake_lca/assets/follower_meshes/link_4_collision.obj
gym_drake_lca/assets/follower_meshes/link_4_collision.stl
gym_drake_lca/assets/follower_meshes/link_4_motor.STL
gym_drake_lca/assets/follower_meshes/link_5.STL
gym_drake_lca/assets/follower_meshes/link_5_collision.mtl
gym_drake_lca/assets/follower_meshes/link_5_collision.obj
gym_drake_lca/assets/follower_meshes/link_5_collision.stl
gym_drake_lca/assets/follower_meshes/link_5_motor.STL
gym_drake_lca/assets/follower_meshes/link_6.STL
gym_drake_lca/assets/follower_meshes/link_6_collision.mtl
gym_drake_lca-0.0.11.dist-info/LICENSE
gym_drake_lca-0.0.11.dist-info/METADATA
gym_drake_lca-0.0.11.dist-info/WHEEL
gym_drake_lca-0.0.11.dist-info/RECORD
