Metadata-Version: 2.1
Name: gym-drake-lca
Version: 0.0.11
Summary: A Gym implementation of the Low Cost Arm (LCA) in the Drake simulator.
Home-page: https://github.com/samzapo/gym-drake-lca
License: Apache-2.0
Author: Samuel Zapolsky
Author-email: samzapo@gmail.com
Requires-Python: >=3.10,<4.0
Classifier: Development Status :: 3 - Alpha
Classifier: Intended Audience :: Developers
Classifier: Intended Audience :: Education
Classifier: Intended Audience :: Science/Research
Classifier: License :: OSI Approved :: Apache Software License
Classifier: Programming Language :: Python :: 3
Classifier: Programming Language :: Python :: 3.10
Classifier: Programming Language :: Python :: 3.11
Classifier: Programming Language :: Python :: 3.12
Classifier: Topic :: Scientific/Engineering :: Artificial Intelligence
Classifier: Topic :: Software Development :: Build Tools
Provides-Extra: dev
Provides-Extra: test
Requires-Dist: debugpy (>=1.8.1) ; extra == "dev"
Requires-Dist: drake (>=1.32.0,<2.0.0)
Requires-Dist: gymnasium (>=0.29.1)
Requires-Dist: imageio[ffmpeg] (>=2.34.0)
Requires-Dist: matplotlib (>=3.9.2)
Requires-Dist: numpy (>=1.26.4)
Requires-Dist: pre-commit (>=3.7.0) ; extra == "dev"
Requires-Dist: pynput (>=1.7.7)
Requires-Dist: pytest (>=8.1.0) ; extra == "test"
Requires-Dist: pytest-cov (>=5.0.0) ; extra == "test"
Project-URL: Repository, https://github.com/samzapo/gym-drake-lca
